{
    "assigns": [
        68.0,
        176.0,
        296.0,
        432.0,
        572.0,
        712.0,
        864.0,
        1024.0,
        1184.0,
        1344.0
    ],
    "comps": [
        23.0,
        65.0,
        111.0,
        170.0,
        226.0,
        278.0,
        339.0,
        406.0,
        477.0,
        544.0
    ],
    "data": {
        "10": [
            [
                34.75,
                "Aditi"
            ],
            [
                24.01,
                "Aditi"
            ],
            [
                34.99,
                "Kunal"
            ],
            [
                24.36,
                "Kunal"
            ],
            [
                32.77,
                "Nikhil"
            ],
            [
                20.97,
                "Nikhil"
            ],
            [
                36.17,
                "Pooja"
            ],
            [
                20.53,
                "Rahul"
            ],
            [
                30.54,
                "Siddharth"
            ],
            [
                28.2,
                "Simran"
            ]
        ],
        "100": [
            [
                34.37,
                "Aarav"
            ],
            [
                21.35,
                "Aarav"
            ],
            [
                30.87,
                "Aditi"
            ],
            [
                27.07,
                "Aditi"
            ],
            [
                22.89,
                "Aditi"
            ],
            [
                32.29,
                "Aditya"
            ],
            [
                29.25,
                "Aditya"
            ],
            [
                25.08,
                "Aditya"
            ],
            [
                20.44,
                "Aditya"
            ],
            [
                36.47,
                "Aman"
            ],
            [
                33.91,
                "Aman"
            ],
            [
                33.7,
                "Aman"
            ],
            [
                33.06,
                "Aman"
            ],
            [
                33.04,
                "Aman"
            ],
            [
                26.04,
                "Aman"
            ],
            [
                34.31,
                "Ananya"
            ],
            [
                24.13,
                "Ananya"
            ],
            [
                23.34,
                "Ananya"
            ],
            [
                22.15,
                "Ananya"
            ],
            [
                22.03,
                "Ananya"
            ],
            [
                21.26,
                "Ananya"
            ],
            [
                21.05,
                "Ananya"
            ],
            [
                34.68,
                "Arjun"
            ],
            [
                32.34,
                "Arjun"
            ],
            [
                28.74,
                "Arjun"
            ],
            [
                25.86,
                "Arjun"
            ],
            [
                24.02,
                "Arjun"
            ],
            [
                21.67,
                "Arjun"
            ],
            [
                37.05,
                "Ishita"
            ],
            [
                36.08,
                "Ishita"
            ],
            [
                35.64,
                "Ishita"
            ],
            [
                32.08,
                "Ishita"
            ],
            [
                29.25,
                "Ishita"
            ],
            [
                39.69,
                "Kavya"
            ],
            [
                38.65,
                "Kavya"
            ],
            [
                35.31,
                "Kavya"
            ],
            [
                35.12,
                "Kavya"
            ],
            [
                33.24,
                "Kavya"
            ],
            [
                32.28,
                "Kavya"
            ],
            [
                31.61,
                "Kavya"
            ],
            [
                29.18,
                "Kavya"
            ],
            [
                28.68,
                "Kavya"
            ],
            [
                39.73,
                "Kunal"
            ],
            [
                36.84,
                "Kunal"
            ],
            [
                36.34,
                "Kunal"
            ],
            [
                30.23,
                "Kunal"
            ],
            [
                27.67,
                "Kunal"
            ],
            [
                39.43,
                "Neha"
            ],
            [
                36.5,
                "Neha"
            ],
            [
                34.8,
                "Neha"
            ],
            [
                34.41,
                "Neha"
            ],
            [
                27.37,
                "Neha"
            ],
            [
                26.05,
                "Neha"
            ],
            [
                24.91,
                "Neha"
            ],
            [
                37.98,
                "Nikhil"
            ],
            [
                29.76,
                "Nikhil"
            ],
            [
                27.72,
                "Nikhil"
            ],
            [
                25.6,
                "Nikhil"
            ],
            [
                25.53,
                "Nikhil"
            ],
            [
                25.43,
                "Nikhil"
            ],
            [
                24.67,
                "Nikhil"
            ],
            [
                22.9,
                "Nikhil"
            ],
            [
                39.92,
                "Pooja"
            ],
            [
                39.47,
                "Pooja"
            ],
            [
                34.82,
                "Pooja"
            ],
            [
                26.68,
                "Pooja"
            ],
            [
                24.11,
                "Pooja"
            ],
            [
                20.95,
                "Pooja"
            ],
            [
                20.58,
                "Pooja"
            ],
            [
                36.32,
                "Priya"
            ],
            [
                26.12,
                "Priya"
            ],
            [
                25.46,
                "Priya"
            ],
            [
                30.59,
                "Rahul"
            ],
            [
                29.42,
                "Rahul"
            ],
            [
                29.17,
                "Rahul"
            ],
            [
                29.16,
                "Rahul"
            ],
            [
                30.28,
                "Riya"
            ],
            [
                28.7,
                "Riya"
            ],
            [
                21.54,
                "Riya"
            ],
            [
                36.51,
                "Rohan"
            ],
            [
                32.52,
                "Rohan"
            ],
            [
                31.66,
                "Rohan"
            ],
            [
                30.07,
                "Rohan"
            ],
            [
                27.81,
                "Rohan"
            ],
            [
                27.78,
                "Rohan"
            ],
            [
                23.09,
                "Rohan"
            ],
            [
                38.26,
                "Siddharth"
            ],
            [
                37.66,
                "Siddharth"
            ],
            [
                33.46,
                "Siddharth"
            ],
            [
                33.36,
                "Siddharth"
            ],
            [
                30.91,
                "Siddharth"
            ],
            [
                27.6,
                "Siddharth"
            ],
            [
                24.79,
                "Siddharth"
            ],
            [
                33.0,
                "Simran"
            ],
            [
                20.65,
                "Simran"
            ],
            [
                35.81,
                "Sneha"
            ],
            [
                34.38,
                "Sneha"
            ],
            [
                21.9,
                "Sneha"
            ],
            [
                35.19,
                "Vivaan"
            ],
            [
                29.36,
                "Vivaan"
            ]
        ],
        "20": [
            [
                38.07,
                "Aarav"
            ],
            [
                37.38,
                "Aarav"
            ],
            [
                34.07,
                "Aarav"
            ],
            [
                39.4,
                "Aditi"
            ],
            [
                32.54,
                "Aditi"
            ],
            [
                20.9,
                "Aman"
            ],
            [
                20.18,
                "Aman"
            ],
            [
                22.89,
                "Arjun"
            ],
            [
                28.21,
                "Kunal"
            ],
            [
                20.96,
                "Pooja"
            ],
            [
                37.21,
                "Priya"
            ],
            [
                22.27,
                "Priya"
            ],
            [
                22.22,
                "Rahul"
            ],
            [
                32.19,
                "Riya"
            ],
            [
                33.59,
                "Rohan"
            ],
            [
                26.58,
                "Siddharth"
            ],
            [
                36.52,
                "Simran"
            ],
            [
                39.27,
                "Sneha"
            ],
            [
                36.32,
                "Sneha"
            ],
            [
                20.25,
                "Vivaan"
            ]
        ],
        "30": [
            [
                38.37,
                "Aditi"
            ],
            [
                29.0,
                "Aditi"
            ],
            [
                25.89,
                "Aditi"
            ],
            [
                39.49,
                "Aditya"
            ],
            [
                30.32,
                "Aditya"
            ],
            [
                31.81,
                "Aman"
            ],
            [
                33.11,
                "Ananya"
            ],
            [
                35.11,
                "Arjun"
            ],
            [
                38.52,
                "Ishita"
            ],
            [
                27.57,
                "Kavya"
            ],
            [
                35.69,
                "Kunal"
            ],
            [
                25.96,
                "Kunal"
            ],
            [
                23.71,
                "Kunal"
            ],
            [
                22.24,
                "Kunal"
            ],
            [
                36.48,
                "Neha"
            ],
            [
                39.15,
                "Pooja"
            ],
            [
                23.19,
                "Pooja"
            ],
            [
                37.46,
                "Priya"
            ],
            [
                38.94,
                "Riya"
            ],
            [
                30.39,
                "Riya"
            ],
            [
                21.33,
                "Riya"
            ],
            [
                33.51,
                "Rohan"
            ],
            [
                29.67,
                "Siddharth"
            ],
            [
                23.82,
                "Siddharth"
            ],
            [
                23.44,
                "Simran"
            ],
            [
                30.6,
                "Sneha"
            ],
            [
                30.15,
                "Sneha"
            ],
            [
                37.97,
                "Vivaan"
            ],
            [
                34.1,
                "Vivaan"
            ],
            [
                32.72,
                "Vivaan"
            ]
        ],
        "40": [
            [
                23.0,
                "Aarav"
            ],
            [
                27.87,
                "Aditi"
            ],
            [
                31.54,
                "Aman"
            ],
            [
                31.19,
                "Aman"
            ],
            [
                33.67,
                "Ananya"
            ],
            [
                31.42,
                "Ananya"
            ],
            [
                29.77,
                "Ananya"
            ],
            [
                25.45,
                "Ananya"
            ],
            [
                39.75,
                "Arjun"
            ],
            [
                21.35,
                "Arjun"
            ],
            [
                20.33,
                "Arjun"
            ],
            [
                29.5,
                "Ishita"
            ],
            [
                26.99,
                "Ishita"
            ],
            [
                26.58,
                "Ishita"
            ],
            [
                25.82,
                "Ishita"
            ],
            [
                38.62,
                "Kavya"
            ],
            [
                34.99,
                "Kavya"
            ],
            [
                27.64,
                "Kunal"
            ],
            [
                24.13,
                "Kunal"
            ],
            [
                25.11,
                "Neha"
            ],
            [
                37.77,
                "Nikhil"
            ],
            [
                31.29,
                "Nikhil"
            ],
            [
                35.39,
                "Pooja"
            ],
            [
                35.15,
                "Priya"
            ],
            [
                28.9,
                "Priya"
            ],
            [
                21.25,
                "Priya"
            ],
            [
                36.82,
                "Rahul"
            ],
            [
                36.59,
                "Rahul"
            ],
            [
                34.26,
                "Rahul"
            ],
            [
                36.52,
                "Riya"
            ],
            [
                23.8,
                "Riya"
            ],
            [
                36.93,
                "Rohan"
            ],
            [
                22.63,
                "Rohan"
            ],
            [
                32.02,
                "Siddharth"
            ],
            [
                31.17,
                "Siddharth"
            ],
            [
                27.07,
                "Siddharth"
            ],
            [
                21.89,
                "Simran"
            ],
            [
                39.54,
                "Sneha"
            ],
            [
                28.23,
                "Sneha"
            ],
            [
                23.37,
                "Sneha"
            ]
        ],
        "50": [
            [
                38.65,
                "Aditi"
            ],
            [
                37.82,
                "Aditi"
            ],
            [
                35.5,
                "Aditya"
            ],
            [
                35.01,
                "Aditya"
            ],
            [
                33.49,
                "Aditya"
            ],
            [
                30.77,
                "Aditya"
            ],
            [
                39.0,
                "Aman"
            ],
            [
                36.56,
                "Aman"
            ],
            [
                25.11,
                "Aman"
            ],
            [
                27.21,
                "Ananya"
            ],
            [
                33.03,
                "Arjun"
            ],
            [
                32.7,
                "Arjun"
            ],
            [
                27.8,
                "Arjun"
            ],
            [
                38.66,
                "Ishita"
            ],
            [
                25.12,
                "Ishita"
            ],
            [
                22.96,
                "Ishita"
            ],
            [
                31.9,
                "Kavya"
            ],
            [
                36.62,
                "Kunal"
            ],
            [
                23.11,
                "Kunal"
            ],
            [
                33.55,
                "Neha"
            ],
            [
                30.52,
                "Neha"
            ],
            [
                33.04,
                "Nikhil"
            ],
            [
                26.37,
                "Pooja"
            ],
            [
                36.2,
                "Priya"
            ],
            [
                31.69,
                "Priya"
            ],
            [
                22.66,
                "Priya"
            ],
            [
                37.45,
                "Rahul"
            ],
            [
                31.52,
                "Rahul"
            ],
            [
                21.84,
                "Rahul"
            ],
            [
                21.37,
                "Rahul"
            ],
            [
                37.97,
                "Riya"
            ],
            [
                37.26,
                "Riya"
            ],
            [
                35.1,
                "Riya"
            ],
            [
                33.19,
                "Riya"
            ],
            [
                29.97,
                "Riya"
            ],
            [
                27.7,
                "Riya"
            ],
            [
                27.01,
                "Riya"
            ],
            [
                34.96,
                "Rohan"
            ],
            [
                30.91,
                "Rohan"
            ],
            [
                24.65,
                "Rohan"
            ],
            [
                24.18,
                "Rohan"
            ],
            [
                21.55,
                "Rohan"
            ],
            [
                26.35,
                "Siddharth"
            ],
            [
                37.7,
                "Simran"
            ],
            [
                24.19,
                "Simran"
            ],
            [
                37.56,
                "Sneha"
            ],
            [
                32.54,
                "Sneha"
            ],
            [
                26.96,
                "Sneha"
            ],
            [
                23.69,
                "Sneha"
            ],
            [
                25.1,
                "Vivaan"
            ]
        ],
        "60": [
            [
                39.57,
                "Aarav"
            ],
            [
                39.29,
                "Aarav"
            ],
            [
                28.54,
                "Aarav"
            ],
            [
                24.35,
                "Aarav"
            ],
            [
                33.63,
                "Aditi"
            ],
            [
                25.54,
                "Aditi"
            ],
            [
                21.05,
                "Aditi"
            ],
            [
                20.35,
                "Aditi"
            ],
            [
                37.93,
                "Aditya"
            ],
            [
                27.43,
                "Aditya"
            ],
            [
                21.81,
                "Aditya"
            ],
            [
                26.98,
                "Aman"
            ],
            [
                25.71,
                "Aman"
            ],
            [
                20.2,
                "Aman"
            ],
            [
                35.69,
                "Ananya"
            ],
            [
                27.25,
                "Ananya"
            ],
            [
                37.97,
                "Arjun"
            ],
            [
                28.74,
                "Arjun"
            ],
            [
                38.98,
                "Ishita"
            ],
            [
                36.28,
                "Ishita"
            ],
            [
                25.09,
                "Ishita"
            ],
            [
                22.09,
                "Ishita"
            ],
            [
                32.0,
                "Kavya"
            ],
            [
                24.4,
                "Kavya"
            ],
            [
                24.78,
                "Kunal"
            ],
            [
                39.19,
                "Neha"
            ],
            [
                29.8,
                "Neha"
            ],
            [
                28.35,
                "Neha"
            ],
            [
                27.96,
                "Neha"
            ],
            [
                22.69,
                "Neha"
            ],
            [
                26.17,
                "Pooja"
            ],
            [
                23.12,
                "Pooja"
            ],
            [
                33.69,
                "Priya"
            ],
            [
                33.35,
                "Priya"
            ],
            [
                24.3,
                "Priya"
            ],
            [
                35.3,
                "Rahul"
            ],
            [
                32.09,
                "Rahul"
            ],
            [
                23.82,
                "Rahul"
            ],
            [
                20.9,
                "Rahul"
            ],
            [
                28.23,
                "Riya"
            ],
            [
                27.77,
                "Riya"
            ],
            [
                24.39,
                "Riya"
            ],
            [
                22.4,
                "Riya"
            ],
            [
                33.36,
                "Rohan"
            ],
            [
                32.16,
                "Rohan"
            ],
            [
                27.04,
                "Rohan"
            ],
            [
                23.71,
                "Rohan"
            ],
            [
                39.42,
                "Siddharth"
            ],
            [
                29.48,
                "Siddharth"
            ],
            [
                28.6,
                "Siddharth"
            ],
            [
                21.16,
                "Siddharth"
            ],
            [
                31.04,
                "Simran"
            ],
            [
                25.91,
                "Simran"
            ],
            [
                24.78,
                "Simran"
            ],
            [
                37.58,
                "Sneha"
            ],
            [
                34.72,
                "Sneha"
            ],
            [
                25.74,
                "Sneha"
            ],
            [
                20.08,
                "Sneha"
            ],
            [
                37.91,
                "Vivaan"
            ],
            [
                35.65,
                "Vivaan"
            ]
        ],
        "70": [
            [
                37.43,
                "Aarav"
            ],
            [
                34.31,
                "Aarav"
            ],
            [
                30.36,
                "Aarav"
            ],
            [
                29.48,
                "Aarav"
            ],
            [
                26.02,
                "Aarav"
            ],
            [
                39.18,
                "Aditi"
            ],
            [
                28.52,
                "Aditi"
            ],
            [
                27.9,
                "Aditi"
            ],
            [
                22.01,
                "Aditi"
            ],
            [
                38.5,
                "Aditya"
            ],
            [
                34.4,
                "Aditya"
            ],
            [
                33.37,
                "Aditya"
            ],
            [
                32.34,
                "Aditya"
            ],
            [
                38.66,
                "Aman"
            ],
            [
                38.52,
                "Aman"
            ],
            [
                33.27,
                "Aman"
            ],
            [
                24.72,
                "Aman"
            ],
            [
                22.89,
                "Aman"
            ],
            [
                36.14,
                "Ananya"
            ],
            [
                28.76,
                "Ananya"
            ],
            [
                25.17,
                "Ananya"
            ],
            [
                23.15,
                "Ananya"
            ],
            [
                39.32,
                "Arjun"
            ],
            [
                28.23,
                "Arjun"
            ],
            [
                24.81,
                "Arjun"
            ],
            [
                23.1,
                "Arjun"
            ],
            [
                34.2,
                "Ishita"
            ],
            [
                31.09,
                "Ishita"
            ],
            [
                26.52,
                "Ishita"
            ],
            [
                32.83,
                "Kavya"
            ],
            [
                23.47,
                "Kavya"
            ],
            [
                29.68,
                "Kunal"
            ],
            [
                29.14,
                "Kunal"
            ],
            [
                26.99,
                "Kunal"
            ],
            [
                25.11,
                "Kunal"
            ],
            [
                33.96,
                "Neha"
            ],
            [
                39.57,
                "Nikhil"
            ],
            [
                37.48,
                "Pooja"
            ],
            [
                35.13,
                "Priya"
            ],
            [
                32.94,
                "Priya"
            ],
            [
                25.4,
                "Priya"
            ],
            [
                22.8,
                "Priya"
            ],
            [
                22.61,
                "Priya"
            ],
            [
                38.17,
                "Rahul"
            ],
            [
                21.76,
                "Rahul"
            ],
            [
                20.64,
                "Rahul"
            ],
            [
                32.76,
                "Riya"
            ],
            [
                28.23,
                "Riya"
            ],
            [
                21.92,
                "Riya"
            ],
            [
                20.91,
                "Riya"
            ],
            [
                38.78,
                "Rohan"
            ],
            [
                33.72,
                "Rohan"
            ],
            [
                27.44,
                "Rohan"
            ],
            [
                36.06,
                "Siddharth"
            ],
            [
                30.5,
                "Siddharth"
            ],
            [
                27.25,
                "Siddharth"
            ],
            [
                38.09,
                "Simran"
            ],
            [
                37.63,
                "Simran"
            ],
            [
                36.42,
                "Simran"
            ],
            [
                33.26,
                "Simran"
            ],
            [
                32.88,
                "Simran"
            ],
            [
                29.05,
                "Simran"
            ],
            [
                28.47,
                "Simran"
            ],
            [
                21.01,
                "Simran"
            ],
            [
                23.31,
                "Sneha"
            ],
            [
                39.07,
                "Vivaan"
            ],
            [
                33.26,
                "Vivaan"
            ],
            [
                32.65,
                "Vivaan"
            ],
            [
                21.26,
                "Vivaan"
            ],
            [
                20.62,
                "Vivaan"
            ]
        ],
        "80": [
            [
                36.78,
                "Aarav"
            ],
            [
                23.44,
                "Aarav"
            ],
            [
                37.94,
                "Aditi"
            ],
            [
                37.86,
                "Aditi"
            ],
            [
                30.77,
                "Aditi"
            ],
            [
                24.23,
                "Aditi"
            ],
            [
                24.15,
                "Aditi"
            ],
            [
                37.87,
                "Aditya"
            ],
            [
                35.23,
                "Aditya"
            ],
            [
                28.9,
                "Aditya"
            ],
            [
                39.59,
                "Aman"
            ],
            [
                37.15,
                "Aman"
            ],
            [
                32.28,
                "Ananya"
            ],
            [
                28.09,
                "Ananya"
            ],
            [
                21.46,
                "Ananya"
            ],
            [
                20.61,
                "Ananya"
            ],
            [
                20.27,
                "Ananya"
            ],
            [
                39.62,
                "Arjun"
            ],
            [
                32.63,
                "Arjun"
            ],
            [
                29.74,
                "Arjun"
            ],
            [
                26.59,
                "Arjun"
            ],
            [
                21.99,
                "Arjun"
            ],
            [
                21.28,
                "Arjun"
            ],
            [
                21.04,
                "Arjun"
            ],
            [
                39.77,
                "Ishita"
            ],
            [
                39.15,
                "Ishita"
            ],
            [
                38.02,
                "Ishita"
            ],
            [
                36.03,
                "Ishita"
            ],
            [
                33.68,
                "Ishita"
            ],
            [
                32.85,
                "Ishita"
            ],
            [
                32.24,
                "Ishita"
            ],
            [
                29.78,
                "Ishita"
            ],
            [
                26.4,
                "Ishita"
            ],
            [
                30.36,
                "Kavya"
            ],
            [
                22.35,
                "Kavya"
            ],
            [
                21.5,
                "Kavya"
            ],
            [
                20.35,
                "Kavya"
            ],
            [
                20.95,
                "Kunal"
            ],
            [
                28.04,
                "Neha"
            ],
            [
                21.79,
                "Neha"
            ],
            [
                20.16,
                "Neha"
            ],
            [
                35.6,
                "Nikhil"
            ],
            [
                33.41,
                "Nikhil"
            ],
            [
                26.55,
                "Nikhil"
            ],
            [
                38.5,
                "Pooja"
            ],
            [
                29.92,
                "Pooja"
            ],
            [
                25.26,
                "Pooja"
            ],
            [
                21.51,
                "Pooja"
            ],
            [
                36.38,
                "Priya"
            ],
            [
                30.74,
                "Priya"
            ],
            [
                30.49,
                "Priya"
            ],
            [
                29.57,
                "Priya"
            ],
            [
                28.94,
                "Priya"
            ],
            [
                27.82,
                "Priya"
            ],
            [
                22.83,
                "Priya"
            ],
            [
                37.28,
                "Rahul"
            ],
            [
                36.0,
                "Rahul"
            ],
            [
                35.75,
                "Rahul"
            ],
            [
                23.18,
                "Rahul"
            ],
            [
                38.72,
                "Riya"
            ],
            [
                37.89,
                "Riya"
            ],
            [
                36.28,
                "Riya"
            ],
            [
                31.72,
                "Riya"
            ],
            [
                29.72,
                "Riya"
            ],
            [
                27.6,
                "Riya"
            ],
            [
                21.7,
                "Riya"
            ],
            [
                20.39,
                "Riya"
            ],
            [
                24.41,
                "Rohan"
            ],
            [
                22.0,
                "Rohan"
            ],
            [
                20.39,
                "Rohan"
            ],
            [
                39.69,
                "Siddharth"
            ],
            [
                36.42,
                "Siddharth"
            ],
            [
                31.12,
                "Siddharth"
            ],
            [
                22.17,
                "Siddharth"
            ],
            [
                39.39,
                "Simran"
            ],
            [
                37.72,
                "Sneha"
            ],
            [
                25.15,
                "Sneha"
            ],
            [
                22.34,
                "Sneha"
            ],
            [
                33.88,
                "Vivaan"
            ],
            [
                32.29,
                "Vivaan"
            ]
        ],
        "90": [
            [
                33.19,
                "Aarav"
            ],
            [
                27.04,
                "Aarav"
            ],
            [
                26.8,
                "Aarav"
            ],
            [
                20.46,
                "Aarav"
            ],
            [
                26.94,
                "Aditi"
            ],
            [
                26.44,
                "Aditi"
            ],
            [
                38.91,
                "Aditya"
            ],
            [
                31.72,
                "Aditya"
            ],
            [
                27.69,
                "Aditya"
            ],
            [
                23.91,
                "Aditya"
            ],
            [
                22.3,
                "Aditya"
            ],
            [
                20.4,
                "Aditya"
            ],
            [
                39.29,
                "Aman"
            ],
            [
                37.71,
                "Aman"
            ],
            [
                33.45,
                "Aman"
            ],
            [
                30.49,
                "Aman"
            ],
            [
                22.61,
                "Aman"
            ],
            [
                35.4,
                "Ananya"
            ],
            [
                35.21,
                "Ananya"
            ],
            [
                35.07,
                "Ananya"
            ],
            [
                26.99,
                "Ananya"
            ],
            [
                39.08,
                "Arjun"
            ],
            [
                35.31,
                "Arjun"
            ],
            [
                34.59,
                "Arjun"
            ],
            [
                33.81,
                "Arjun"
            ],
            [
                32.4,
                "Arjun"
            ],
            [
                29.12,
                "Arjun"
            ],
            [
                26.84,
                "Arjun"
            ],
            [
                20.6,
                "Arjun"
            ],
            [
                39.51,
                "Ishita"
            ],
            [
                35.01,
                "Ishita"
            ],
            [
                29.7,
                "Ishita"
            ],
            [
                28.84,
                "Ishita"
            ],
            [
                25.54,
                "Ishita"
            ],
            [
                39.06,
                "Kavya"
            ],
            [
                27.02,
                "Kavya"
            ],
            [
                33.12,
                "Kunal"
            ],
            [
                29.24,
                "Kunal"
            ],
            [
                36.58,
                "Neha"
            ],
            [
                30.99,
                "Neha"
            ],
            [
                27.82,
                "Neha"
            ],
            [
                27.39,
                "Neha"
            ],
            [
                26.35,
                "Neha"
            ],
            [
                26.06,
                "Neha"
            ],
            [
                25.56,
                "Neha"
            ],
            [
                38.02,
                "Nikhil"
            ],
            [
                31.83,
                "Nikhil"
            ],
            [
                37.03,
                "Pooja"
            ],
            [
                30.06,
                "Pooja"
            ],
            [
                27.42,
                "Pooja"
            ],
            [
                22.42,
                "Pooja"
            ],
            [
                21.73,
                "Pooja"
            ],
            [
                37.96,
                "Priya"
            ],
            [
                31.83,
                "Priya"
            ],
            [
                29.17,
                "Priya"
            ],
            [
                27.38,
                "Priya"
            ],
            [
                25.25,
                "Priya"
            ],
            [
                36.09,
                "Rahul"
            ],
            [
                35.74,
                "Rahul"
            ],
            [
                31.02,
                "Rahul"
            ],
            [
                22.63,
                "Rahul"
            ],
            [
                26.1,
                "Riya"
            ],
            [
                39.62,
                "Rohan"
            ],
            [
                38.1,
                "Rohan"
            ],
            [
                38.03,
                "Rohan"
            ],
            [
                36.01,
                "Rohan"
            ],
            [
                35.82,
                "Rohan"
            ],
            [
                35.22,
                "Rohan"
            ],
            [
                32.39,
                "Rohan"
            ],
            [
                29.45,
                "Rohan"
            ],
            [
                29.15,
                "Rohan"
            ],
            [
                26.63,
                "Rohan"
            ],
            [
                20.62,
                "Rohan"
            ],
            [
                20.54,
                "Rohan"
            ],
            [
                33.36,
                "Siddharth"
            ],
            [
                23.7,
                "Siddharth"
            ],
            [
                22.66,
                "Siddharth"
            ],
            [
                28.33,
                "Simran"
            ],
            [
                26.26,
                "Simran"
            ],
            [
                25.41,
                "Simran"
            ],
            [
                23.35,
                "Simran"
            ],
            [
                37.16,
                "Sneha"
            ],
            [
                32.51,
                "Sneha"
            ],
            [
                26.6,
                "Sneha"
            ],
            [
                25.68,
                "Sneha"
            ],
            [
                22.69,
                "Sneha"
            ],
            [
                21.72,
                "Sneha"
            ],
            [
                35.18,
                "Vivaan"
            ],
            [
                34.37,
                "Vivaan"
            ],
            [
                28.83,
                "Vivaan"
            ]
        ]
    }
}